damn_tool/__init__.py
damn_tool/ls.py
damn_tool/metrics.py
damn_tool/show.py
damn_tool/utils/adapters/data_warehouses/base.py
damn_tool/utils/adapters/data_warehouses/bigquery.py
damn_tool/utils/adapters/data_warehouses/snowflake.py
damn_tool/utils/adapters/io_managers/aws.py
damn_tool/utils/adapters/io_managers/base.py
damn_tool/utils/adapters/orchestrators/base.py
damn_tool/utils/adapters/orchestrators/dagster.py
damn_tool/utils/helpers.py
damn_tool-0.1.5.dist-info/METADATA
damn_tool-0.1.5.dist-info/WHEEL
damn_tool-0.1.5.dist-info/entry_points.txt
damn_tool-0.1.5.dist-info/RECORD
