Metadata-Version: 2.1
Name: damn-tool
Version: 0.1.5
Summary: The DAMN (Data Assets Metric Navigation) tool extracts and reports metrics about your data assets
Author: Olivier Dupuis
Author-email: olivier@republicofdata.io
Requires-Python: >=3.9,<4.0
Classifier: Programming Language :: Python :: 3
Classifier: Programming Language :: Python :: 3.9
Classifier: Programming Language :: Python :: 3.10
Classifier: Programming Language :: Python :: 3.11
Classifier: Programming Language :: Python :: 3.12
Requires-Dist: boto3 (>=1.28.1,<2.0.0)
Requires-Dist: click (>=8.1.3,<9.0.0)
Requires-Dist: google-cloud-bigquery (>=3.27.0,<4.0.0)
Requires-Dist: jinja2 (>=3.1.2,<4.0.0)
Requires-Dist: line-profiler (>=4.0.3,<5.0.0)
Requires-Dist: pyperclip (>=1.8.2,<2.0.0)
Requires-Dist: python-dotenv (>=1.0.0,<2.0.0)
Requires-Dist: pyyaml (>=6.0,<7.0)
Requires-Dist: requests (>=2.31.0,<3.0.0)
Requires-Dist: snowflake-connector-python (>=3.0.4,<4.0.0)
Requires-Dist: termcolor (>=2.3.0,<3.0.0)
